NetkillerNetwork/README.md
NetkillerNetwork/__init__.py
NetkillerNetwork/__main__.py
NetkillerNetwork/file.epub
NetkillerNetwork/index.html
NetkillerNetwork/css/__init__.py
NetkillerNetwork/css/annotations.css
NetkillerNetwork/css/main.css
NetkillerNetwork/css/normalize.css
NetkillerNetwork/css/popup.css
NetkillerNetwork/font/__init__.py
NetkillerNetwork/font/fontello.eot
NetkillerNetwork/font/fontello.svg
NetkillerNetwork/font/fontello.ttf
NetkillerNetwork/font/fontello.woff
NetkillerNetwork/img/__init__.py
NetkillerNetwork/img/annotator-glyph-sprite.png
NetkillerNetwork/img/annotator-icon-sprite.png
NetkillerNetwork/img/apple-touch-icon.png
NetkillerNetwork/img/cancelfullscreen.png
NetkillerNetwork/img/close.png
NetkillerNetwork/img/fullscreen.png
NetkillerNetwork/img/loader.gif
NetkillerNetwork/img/menu-icon.png
NetkillerNetwork/img/save.png
NetkillerNetwork/img/saved.png
NetkillerNetwork/img/settings-s.png
NetkillerNetwork/img/settings.png
NetkillerNetwork/img/star.png
NetkillerNetwork/js/__init__.py
NetkillerNetwork/js/epub.js
NetkillerNetwork/js/epub.min.js
NetkillerNetwork/js/epub.min.map
NetkillerNetwork/js/hooks.min.js
NetkillerNetwork/js/hooks.min.map
NetkillerNetwork/js/reader.js
NetkillerNetwork/js/reader.js.map
NetkillerNetwork/js/reader.min.js
NetkillerNetwork/js/reader.min.map
NetkillerNetwork/js/hooks/__init__.py
NetkillerNetwork/js/hooks/extensions/__init__.py
NetkillerNetwork/js/hooks/extensions/highlight.js
NetkillerNetwork/js/libs/__init__.py
NetkillerNetwork/js/libs/jquery.min.js
NetkillerNetwork/js/libs/localforage.min.js
NetkillerNetwork/js/libs/screenfull.js
NetkillerNetwork/js/libs/screenfull.min.js
NetkillerNetwork/js/libs/zip.min.js
NetkillerNetwork/js/plugins/__init__.py
NetkillerNetwork/js/plugins/hypothesis.js
NetkillerNetwork/js/plugins/search.js
netkiller_network-2024.3.5.0.dist-info/METADATA
netkiller_network-2024.3.5.0.dist-info/WHEEL
netkiller_network-2024.3.5.0.dist-info/entry_points.txt
netkiller_network-2024.3.5.0.dist-info/top_level.txt
netkiller_network-2024.3.5.0.dist-info/RECORD
